{
  "main": {
    "id": "c46b414494b6c301",
    "type": "split",
    "children": [
      {
        "id": "af84ee23c05702e0",
        "type": "tabs",
        "children": [
          {
            "id": "fa02f46e5fd6eac8",
            "type": "leaf",
            "state": {
              "type": "markdown",
              "state": {
                "file": "BETA.md",
                "mode": "source",
                "source": false
              }
            }
          },
          {
            "id": "f211bd74fa1efb43",
            "type": "leaf",
            "state": {
              "type": "markdown",
              "state": {
                "file": "security/REFERENCES.md",
                "mode": "source",
                "source": false
              }
            }
          },
          {
            "id": "254d42c38914a4f4",
            "type": "leaf",
            "state": {
              "type": "markdown",
              "state": {
                "file": "legal/INTELLECTUAL_PROPERTY.md",
                "mode": "source",
                "source": false
              }
            }
          },
          {
            "id": "7209060f4f0f48df",
            "type": "leaf",
            "state": {
              "type": "markdown",
              "state": {
                "file": "UNORGANIZED.md",
                "mode": "source",
                "source": false
              }
            }
          },
          {
            "id": "db2150027e839aba",
            "type": "leaf",
            "state": {
              "type": "markdown",
              "state": {
                "file": "sharing/INFORMATION_SHARING.md",
                "mode": "source",
                "source": false
              }
            }
          },
          {
            "id": "69fea27a06c605a1",
            "type": "leaf",
            "state": {
              "type": "markdown",
              "state": {
                "file": "technical/TECH_STACK.md",
                "mode": "source",
                "source": false
              }
            }
          },
          {
            "id": "62f504e3ded0fb1b",
            "type": "leaf",
            "state": {
              "type": "markdown",
              "state": {
                "file": "ROADMAP.md",
                "mode": "source",
                "source": false
              }
            }
          },
          {
            "id": "349b9eacdfb1535b",
            "type": "leaf",
            "state": {
              "type": "markdown",
              "state": {
                "file": "legal/sources/CERNER.md",
                "mode": "source",
                "source": false
              }
            }
          },
          {
            "id": "7666acd8e70d5e00",
            "type": "leaf",
            "state": {
              "type": "markdown",
              "state": {
                "file": "security/REFERENCES.md",
                "mode": "source",
                "source": false
              }
            }
          },
          {
            "id": "b56d17a0c7423e14",
            "type": "leaf",
            "state": {
              "type": "markdown",
              "state": {
                "file": "ROADMAP.md",
                "mode": "source",
                "source": false
              }
            }
          },
          {
            "id": "30f120e5307f9270",
            "type": "leaf",
            "state": {
              "type": "markdown",
              "state": {
                "file": "technical/SOFTWARE.md",
                "mode": "source",
                "source": false
              }
            }
          }
        ],
        "currentTab": 10
      }
    ],
    "direction": "vertical"
  },
  "left": {
    "id": "fada86f015b6cddd",
    "type": "split",
    "children": [
      {
        "id": "5863e178a8c77b8d",
        "type": "tabs",
        "children": [
          {
            "id": "8360a188f8a1d092",
            "type": "leaf",
            "state": {
              "type": "file-explorer",
              "state": {
                "sortOrder": "alphabetical"
              }
            }
          },
          {
            "id": "237732b2ceb60fc0",
            "type": "leaf",
            "state": {
              "type": "search",
              "state": {
                "query": "tag:#Features",
                "matchingCase": false,
                "explainSearch": false,
                "collapseAll": false,
                "extraContext": false,
                "sortOrder": "alphabetical"
              }
            }
          },
          {
            "id": "034f7db69007d656",
            "type": "leaf",
            "state": {
              "type": "starred",
              "state": {}
            }
          }
        ]
      }
    ],
    "direction": "horizontal",
    "width": 248.5
  },
  "right": {
    "id": "58178119e53f4ea1",
    "type": "split",
    "children": [
      {
        "id": "a102da58362298fc",
        "type": "tabs",
        "children": [
          {
            "id": "15436eae74adfbde",
            "type": "leaf",
            "state": {
              "type": "backlink",
              "state": {
                "file": "technical/SOFTWARE.md",
                "collapseAll": false,
                "extraContext": false,
                "sortOrder": "alphabetical",
                "showSearch": false,
                "searchQuery": "",
                "backlinkCollapsed": false,
                "unlinkedCollapsed": true
              }
            }
          },
          {
            "id": "4655b5a47e00b6a0",
            "type": "leaf",
            "state": {
              "type": "outgoing-link",
              "state": {
                "file": "technical/SOFTWARE.md",
                "linksCollapsed": false,
                "unlinkedCollapsed": true
              }
            }
          },
          {
            "id": "bba77bbb21bd385c",
            "type": "leaf",
            "state": {
              "type": "tag",
              "state": {
                "sortOrder": "frequency",
                "useHierarchy": true
              }
            }
          },
          {
            "id": "c1ee2f76490bd8f5",
            "type": "leaf",
            "state": {
              "type": "outline",
              "state": {
                "file": "technical/SOFTWARE.md"
              }
            }
          }
        ]
      }
    ],
    "direction": "horizontal",
    "width": 300,
    "collapsed": true
  },
  "ribbon": {
    "mostRecentAction": ""
  },
  "active": "30f120e5307f9270",
  "lastOpenFiles": [
    "technical/TECH_STACK.md",
    "technical/ARCHITECTURE.md",
    "technical/AUTHENTICATION.md",
    "PATIENT_PORTAL_AND_SOURCES_TESTING.md",
    "ROADMAP.md",
    "TODO_TASKS.md",
    "legal/CORP.md",
    "README.md",
    "technical/SINGLE_PAGE_APP.md",
    "technical/ANALYTICS.md"
  ]
}